{
  "game": "wend",
  "puzzleNumber": 17,
  "date": "2026-06-25",
  "dateLabel": "June 25, 2026",
  "updatedAt": "2026-06-25T07:20:00Z",
  "difficulty": "Medium",
  "grid": [
    ["Y", "O", "T", "S", "P", "I"],
    ["C", "U", null, null, null, "R"],
    ["T", "A", "U", "A", null, "A"],
    ["I", null, "Q", "N", "T", "L"],
    ["O", null, null, null, "I", "T"],
    ["N", "R", "A", "C", "K", "Y"]
  ],
  "hints": [
    {
      "level": 1,
      "title": "Gentle nudge",
      "text": "This board has the same 6x6 letter layout and blocked cells shown in the LinkedIn screenshot."
    },
    {
      "level": 2,
      "title": "Direction clue",
      "text": "Official answer paths are still pending verification."
    },
    {
      "level": 3,
      "title": "Almost there",
      "text": "Do not use the old placeholder answer set for this LinkedIn board."
    }
  ],
  "answers": [],
  "explanation": "The visible board now matches the LinkedIn Wend screenshot: a 6x6 letter grid with two gray blocked-wall regions. Official answer words and paths are intentionally withheld until verified.",
  "quickHint": "Board captured from the LinkedIn screenshot; answers pending verification.",
  "fastTip": "Use only verified official paths before publishing answer reveals.",
  "commonMistake": "Do not reuse the old placeholder 5x5 answer set for the real LinkedIn board.",
  "difficultyNote": "Pending until the official answer word lengths and paths are verified.",
  "relatedGames": [],
  "isVerified": false
}
